itsim_project_creation_library/__init__.py
itsim_project_creation_library/feed_processing.py
itsim_project_creation_library/gis_processing.py
itsim_project_creation_library/utils.py
itsim_project_creation_library-0.3.0.dist-info/LICENSE
itsim_project_creation_library-0.3.0.dist-info/METADATA
itsim_project_creation_library-0.3.0.dist-info/WHEEL
itsim_project_creation_library-0.3.0.dist-info/top_level.txt
itsim_project_creation_library-0.3.0.dist-info/RECORD
